aisible/__init__.py
aisible/aisible.py
aisible-0.2.0.dist-info/LICENSE
aisible-0.2.0.dist-info/METADATA
aisible-0.2.0.dist-info/WHEEL
aisible-0.2.0.dist-info/entry_points.txt
aisible-0.2.0.dist-info/top_level.txt
aisible-0.2.0.dist-info/RECORD
