Metadata-Version: 2.1
Name: aisible
Version: 0.2.0
Summary: A tool to run Ansible commands and analyze output with LLMs
Home-page: https://github.com/etapsc/AIsible
Author: Kullat Nunu
Author-email: ak@etapiscium.com
Classifier: Development Status :: 3 - Alpha
Classifier: Intended Audience :: Developers
Classifier: License :: OSI Approved :: MIT License
Classifier: Operating System :: OS Independent
Classifier: Programming Language :: Python :: 3
Classifier: Programming Language :: Python :: 3.7
Classifier: Programming Language :: Python :: 3.8
Classifier: Programming Language :: Python :: 3.9
Classifier: Programming Language :: Python :: 3.10
Classifier: Programming Language :: Python :: 3.11
Requires-Python: >=3.7
License-File: LICENSE
Requires-Dist: ansible-runner ==2.4.0
Requires-Dist: anthropic ==0.34.1
Requires-Dist: openai ==1.42.0
Requires-Dist: PyYAML ==6.0.2
Requires-Dist: google-generativeai ==0.7.2
